<CADRosterView><LoadFor><service>F</service><districtid>T48</districtid><shiftid>1</shiftid><startdatetime>05082024 0800</startdatetime><enddatetime>05092024 0800</enddatetime><date>05082024</date></LoadFor><Table><apparatusid>T48</apparatusid><startdatetime>05082024 0800</startdatetime><enddatetime>05092024 0800</enddatetime><personnelid>FR2767</personnelid><radioid /><vehicleid /></Table><Table><apparatusid>T48</apparatusid><startdatetime>05082024 0800</startdatetime><enddatetime>05092024 0800</enddatetime><personnelid>SI5277</personnelid><radioid /><vehicleid /></Table><Table><apparatusid>T48</apparatusid><startdatetime>05082024 0800</startdatetime><enddatetime>05092024 0800</enddatetime><personnelid>NO2110</personnelid><radioid /><vehicleid /></Table><Table><apparatusid>T48</apparatusid><startdatetime>05082024 0800</startdatetime><enddatetime>05092024 0800</enddatetime><personnelid>WO2460</personnelid><radioid /><vehicleid /></Table></CADRosterView>