<CADRosterView><LoadFor><service>F</service><districtid>E08</districtid><shiftid>1</shiftid><startdatetime>05092024 0800</startdatetime><enddatetime>05102024 0800</enddatetime><date>05092024</date></LoadFor><Table><apparatusid>E08</apparatusid><startdatetime>05092024 0800</startdatetime><enddatetime>05102024 0800</enddatetime><personnelid>CH1691</personnelid><radioid /><vehicleid /></Table><Table><apparatusid>E08</apparatusid><startdatetime>05092024 0800</startdatetime><enddatetime>05102024 0800</enddatetime><personnelid>RU2198</personnelid><radioid /><vehicleid /></Table><Table><apparatusid>E08</apparatusid><startdatetime>05092024 0800</startdatetime><enddatetime>05102024 0800</enddatetime><personnelid>MA7955</personnelid><radioid /><vehicleid /></Table><Table><apparatusid>E08</apparatusid><startdatetime>05092024 0800</startdatetime><enddatetime>05102024 0800</enddatetime><personnelid>CA3787</personnelid><radioid /><vehicleid /></Table></CADRosterView>